odoo/addons/web_widget_remote_measure_utilcell/README.rst
odoo/addons/web_widget_remote_measure_utilcell/__init__.py
odoo/addons/web_widget_remote_measure_utilcell/__manifest__.py
odoo/addons/web_widget_remote_measure_utilcell/docs/Es_MAN_MatrixII_Utilcell_v1.009x_1611.pdf
odoo/addons/web_widget_remote_measure_utilcell/i18n/es.pot
odoo/addons/web_widget_remote_measure_utilcell/i18n/it.po
odoo/addons/web_widget_remote_measure_utilcell/i18n/web_widget_remote_measure_utilcell.pot
odoo/addons/web_widget_remote_measure_utilcell/models/__init__.py
odoo/addons/web_widget_remote_measure_utilcell/models/remote_measure_device.py
odoo/addons/web_widget_remote_measure_utilcell/readme/CONFIGURE.md
odoo/addons/web_widget_remote_measure_utilcell/readme/CONTRIBUTORS.md
odoo/addons/web_widget_remote_measure_utilcell/readme/DESCRIPTION.md
odoo/addons/web_widget_remote_measure_utilcell/readme/ROADMAP.md
odoo/addons/web_widget_remote_measure_utilcell/static/description/icon.png
odoo/addons/web_widget_remote_measure_utilcell/static/description/index.html
odoo/addons/web_widget_remote_measure_utilcell/static/src/js/protocol_utilcell.esm.js
odoo_addon_web_widget_remote_measure_utilcell-17.0.1.0.1.2.dist-info/METADATA
odoo_addon_web_widget_remote_measure_utilcell-17.0.1.0.1.2.dist-info/WHEEL
odoo_addon_web_widget_remote_measure_utilcell-17.0.1.0.1.2.dist-info/top_level.txt
odoo_addon_web_widget_remote_measure_utilcell-17.0.1.0.1.2.dist-info/RECORD
